kafka_rest_client-0.8.0.dist-info/DESCRIPTION.rst
kafka_rest_client-0.8.0.dist-info/METADATA
kafka_rest_client-0.8.0.dist-info/RECORD
kafka_rest_client-0.8.0.dist-info/WHEEL
kafka_rest_client-0.8.0.dist-info/metadata.json
kafka_rest_client-0.8.0.dist-info/top_level.txt
proofpoint/__init__.py
proofpoint/kafka/ConsumerFactory.py
proofpoint/kafka/InfobusConsumer.py
proofpoint/kafka/KafkaRestConsumer.py
proofpoint/kafka/__init__.py
proofpoint/kafka/errors.py
