Metadata-Version: 2.0
Name: kafka-rest-client
Version: 0.8.0
Summary: A python kafka rest client
Home-page: https://github.com/pypa/sampleproject
Author: Chaitanya Puchakayala
Author-email: x-tap-jab@proofpoint.com
License: MIT
Keywords: Kafka rest client library
Platform: UNKNOWN
Classifier: Development Status :: 3 - Alpha
Classifier: Intended Audience :: Developers
Classifier: Topic :: Software Development :: Build Tools
Classifier: License :: OSI Approved :: MIT License
Classifier: Programming Language :: Python :: 2
Classifier: Programming Language :: Python :: 2.7
Classifier: Programming Language :: Python :: 3
Classifier: Programming Language :: Python :: 3.3
Classifier: Programming Language :: Python :: 3.4
Classifier: Programming Language :: Python :: 3.5
Requires-Dist: oauthlib
Requires-Dist: peppercorn
Requires-Dist: requests
Requires-Dist: requests-oauthlib
Requires-Dist: validators
Provides-Extra: dev
Requires-Dist: check-manifest; extra == 'dev'
Provides-Extra: test
Requires-Dist: coverage; extra == 'test'
